.gitignore
.gitlab-ci.yml
.style.yapf
CHANGELOG.md
LICENSE
Makefile
README.md
VERSION
setup.cfg
setup.py
balsamish.egg-info/PKG-INFO
balsamish.egg-info/SOURCES.txt
balsamish.egg-info/dependency_links.txt
balsamish.egg-info/requires.txt
balsamish.egg-info/top_level.txt
requirements/lib.txt
requirements/publish.txt
requirements/test.txt
src/balsam/__init__.py
src/balsam/schema/__init__.py
src/balsam/schema/base.py
src/balsam/schema/validators.py
src/balsam/selection/__init__.py
src/balsam/selection/base.py
src/balsam/selection/from_dict.py
src/balsam/store/__init__.py
src/balsam/store/encoder.py
src/balsam/store/refs.py
src/balsam/store/store.py
src/balsam/tasks/__init__.py
src/balsam/tasks/abstract.py
src/balsam/tasks/cli.py
src/balsam/tasks/graph.py
test/test_balsam/__init__.py
test/test_balsam/utils.py
test/test_balsam/fixtures/df.csv
test/test_balsam/schema/test_base.py
test/test_balsam/selection/__init__.py
test/test_balsam/selection/test_base.py
test/test_balsam/selection/test_from_dict.py
test/test_balsam/store/test_store.py
test/test_balsam/tasks/__init__.py
test/test_balsam/tasks/test_cli.py